lb_toolkits/__init__.py
lb_toolkits/downloadcentre.py
lb_toolkits/version.py
lb_toolkits/DataCollections/ASF.py
lb_toolkits/DataCollections/CDDIS.py
lb_toolkits/DataCollections/DataCollectionDefinition.py
lb_toolkits/DataCollections/EARTHCARE.py
lb_toolkits/DataCollections/ERA5.py
lb_toolkits/DataCollections/ESA.py
lb_toolkits/DataCollections/EUMDAC.py
lb_toolkits/DataCollections/GES_DISC.py
lb_toolkits/DataCollections/GHRC_DAAC.py
lb_toolkits/DataCollections/JMA.py
lb_toolkits/DataCollections/LAADS.py
lb_toolkits/DataCollections/LANCEAMSR2.py
lb_toolkits/DataCollections/LANCEMODIS.py
lb_toolkits/DataCollections/LARC.py
lb_toolkits/DataCollections/LARC_ASDC.py
lb_toolkits/DataCollections/LARC_CLOUD.py
lb_toolkits/DataCollections/LM_FIRMS.py
lb_toolkits/DataCollections/LPCLOUD.py
lb_toolkits/DataCollections/LPDAAC_ECS.py
lb_toolkits/DataCollections/NOAA.py
lb_toolkits/DataCollections/NSIDCV0.py
lb_toolkits/DataCollections/NSIDC_CPRD.py
lb_toolkits/DataCollections/NSIDC_ECS.py
lb_toolkits/DataCollections/OB_DAAC.py
lb_toolkits/DataCollections/OMINRT.py
lb_toolkits/DataCollections/ORNL_CLOUD.py
lb_toolkits/DataCollections/OTHER.py
lb_toolkits/DataCollections/POCLOUD.py
lb_toolkits/DataCollections/SEDAC.py
lb_toolkits/DataCollections/USGS.py
lb_toolkits/DataCollections/USGS_EROS.py
lb_toolkits/DataCollections/USGS_LTA.py
lb_toolkits/DataCollections/__init__.py
lb_toolkits/docs/provider/ASF.json
lb_toolkits/docs/provider/CDDIS.json
lb_toolkits/docs/provider/GES_DISC.json
lb_toolkits/docs/provider/GHRC_DAAC.json
lb_toolkits/docs/provider/LAADS.json
lb_toolkits/docs/provider/LANCEAMSR2.json
lb_toolkits/docs/provider/LANCEMODIS.json
lb_toolkits/docs/provider/LARC.json
lb_toolkits/docs/provider/LARC_ASDC.json
lb_toolkits/docs/provider/LARC_CLOUD.json
lb_toolkits/docs/provider/LM_FIRMS.json
lb_toolkits/docs/provider/LPCLOUD.json
lb_toolkits/docs/provider/LPDAAC_ECS.json
lb_toolkits/docs/provider/NSIDCV0.json
lb_toolkits/docs/provider/NSIDC_CPRD.json
lb_toolkits-25.10.11.dist-info/LICENSE
lb_toolkits-25.10.11.dist-info/METADATA
lb_toolkits-25.10.11.dist-info/WHEEL
lb_toolkits-25.10.11.dist-info/entry_points.txt
lb_toolkits-25.10.11.dist-info/namespace_packages.txt
lb_toolkits-25.10.11.dist-info/top_level.txt
lb_toolkits-25.10.11.dist-info/RECORD
