Metadata-Version: 2.1
Name: lb_toolkits
Version: 25.10.11
Summary: lb_toolkits Library for Meteorology and Remote Sensing
Home-page: https://github.com/libin033/lb_toolkits
Author: Nanhu Lab(南湖实验室，浙江.嘉兴)
License: MIT
Keywords: FengYun,MODIS,Sentinel,landsat,Meteorology,RemoteSensing,spider,ftp,sftp
Platform: windows
Platform: linux
Classifier: Development Status :: 3 - Alpha
Classifier: Intended Audience :: Developers
Classifier: Intended Audience :: Science/Research
Classifier: Topic :: Scientific/Engineering
Classifier: License :: OSI Approved :: MIT License
Classifier: Programming Language :: Python :: 3
Requires-Python: >=3.7
License-File: LICENSE
Requires-Dist: numpy>=1.2.0
Requires-Dist: tqdm>=4.0.0
Requires-Dist: paramiko>=2.10.0
Requires-Dist: cdsapi>=0.5.0
Requires-Dist: sphinx-rtd-theme>=1.3
Requires-Dist: beautifulsoup4>=4.10
Requires-Dist: geojson>=2.4
Requires-Dist: geomet>=0.3
Requires-Dist: html2text>=2
Requires-Dist: python-dateutil>=2.0
Requires-Dist: certifi>=2017.4.17
Requires-Dist: click>=7.1
Requires-Dist: imapclient>2.0
